pywiz.py
pywiz-0.0.13.dist-info/METADATA
pywiz-0.0.13.dist-info/RECORD
pywiz-0.0.13.dist-info/WHEEL
pywiz-0.0.13.dist-info/top_level.txt
