Metadata-Version: 2.1
Name: pywiz
Version: 0.0.13
Summary: A PyQt5 wizard package
Home-page: https://github.com/xxRonaldxx/pywiz
Author: xxRonaldxx
Author-email: xxRonaldxx@someplace.com
License: MIT
Platform: UNKNOWN
Classifier: Development Status :: 2 - Pre-Alpha
Classifier: Environment :: Win32 (MS Windows)
Classifier: Intended Audience :: Financial and Insurance Industry
Classifier: Topic :: Office/Business :: Financial :: Spreadsheet
Classifier: Programming Language :: Python :: 3.6
Classifier: License :: OSI Approved :: MIT License
Classifier: Operating System :: OS Independent
Classifier: Natural Language :: English
Requires-Dist: PyQt5
